gibson_dataset/Sample.py
gibson_dataset/__init__.py
gibson_dataset/__version__.py
gibson_dataset/utilities/__init__.py
gibson_dataset/utilities/color.py
gibson_dataset/utilities/engine_selector.py
gibson_dataset-0.1.2.dist-info/LICENSE
gibson_dataset-0.1.2.dist-info/METADATA
gibson_dataset-0.1.2.dist-info/WHEEL
gibson_dataset-0.1.2.dist-info/entry_points.txt
gibson_dataset-0.1.2.dist-info/top_level.txt
gibson_dataset-0.1.2.dist-info/RECORD
