Metadata-Version: 2.1
Name: gibson-dataset
Version: 0.1.2
Summary: Gibson dataset
Home-page: https://github.com/micheleantonazzi/gibson-dataset
Author: Michele Antonazzi
Author-email: micheleantonazzi@gmail.com
License: MIT
Platform: UNKNOWN
Classifier: Development Status :: 3 - Alpha
Classifier: License :: OSI Approved :: MIT License
Classifier: Programming Language :: Python :: 3
Requires-Dist: numpy
Provides-Extra: test
Requires-Dist: pytest ; extra == 'test'
Requires-Dist: pytest-cov ; extra == 'test'
